{
  "rasa_nlu_data": {
    "common_examples": [
      {
        "text": "button form",
        "intent": "buttonform",
        "entities": [],
        "metadata": {
          "language": "en",
          "canonical": true
        }
      },
      {
        "text": "f",
        "intent": "buttonform",
        "entities": [],
        "metadata": {
          "language": "en"
        }
      },
      {
        "text": "form",
        "intent": "buttonform",
        "entities": [],
        "metadata": {
          "language": "en"
        }
      },
      {
        "text": "dislike",
        "intent": "dislike_intent",
        "entities": [],
        "metadata": {
          "language": "en"
        }
      },
      {
        "text": "dislike intent",
        "intent": "dislike_intent",
        "entities": [],
        "metadata": {
          "language": "en"
        }
      },
      {
        "text": "dislike_intent",
        "intent": "dislike_intent",
        "entities": [],
        "metadata": {
          "language": "en"
        }
      },
      {
        "text": "feedback_1",
        "intent": "feedback_1",
        "entities": [],
        "metadata": {
          "language": "en"
        }
      },
      {
        "text": "feedback_2",
        "intent": "feedback_2",
        "entities": [],
        "metadata": {
          "language": "en"
        }
      },
      {
        "text": "feedback_3",
        "intent": "feedback_3",
        "entities": [],
        "metadata": {
          "language": "en"
        }
      },
      {
        "text": "hi img",
        "intent": "img",
        "entities": [],
        "metadata": {
          "language": "en",
          "canonical": true
        }
      },
      {
        "text": "like",
        "intent": "like_intent",
        "entities": [],
        "metadata": {
          "language": "en"
        }
      },
      {
        "text": "like intent",
        "intent": "like_intent",
        "entities": [],
        "metadata": {
          "language": "en"
        }
      },
      {
        "text": "like_intent",
        "intent": "like_intent",
        "entities": [],
        "metadata": {
          "language": "en"
        }
      },
      {
        "text": "star value 1",
        "intent": "star_value_1",
        "entities": [],
        "metadata": {
          "language": "en",
          "canonical": true
        }
      },
      {
        "text": "star value1",
        "intent": "star_value_1",
        "entities": [],
        "metadata": {
          "language": "en"
        }
      },
      {
        "text": "star",
        "intent": "starratingform",
        "entities": [],
        "metadata": {
          "language": "en"
        }
      },
      {
        "text": "star rating form",
        "intent": "starratingform",
        "entities": [],
        "metadata": {
          "language": "en"
        }
      },
      {
        "text": "starrating",
        "intent": "starratingform",
        "entities": [],
        "metadata": {
          "language": "en"
        }
      },
      {
        "text": "starrating form",
        "intent": "starratingform",
        "entities": [],
        "metadata": {
          "language": "en",
          "canonical": true
        }
      },
      {
        "text": "starratingform",
        "intent": "starratingform",
        "entities": [],
        "metadata": {
          "language": "en"
        }
      },
      {
        "text": "stars",
        "intent": "starratingform",
        "entities": [],
        "metadata": {
          "language": "en"
        }
      },
      {
        "text": "feed",
        "intent": "test_feedback",
        "entities": [],
        "metadata": {
          "language": "en"
        }
      },
      {
        "text": "feedback form",
        "intent": "test_feedback",
        "entities": [],
        "metadata": {
          "language": "en"
        }
      },
      {
        "text": "feedbackform",
        "intent": "test_feedback",
        "entities": [],
        "metadata": {
          "language": "en"
        }
      },
      {
        "text": "test feedback",
        "intent": "test_feedback",
        "entities": [],
        "metadata": {
          "language": "en",
          "canonical": true
        }
      },
      {
        "text": "value1",
        "intent": "value1",
        "entities": [],
        "metadata": {
          "language": "en",
          "canonical": true
        }
      }
    ],
    "entity_synonyms": [],
    "gazette": [],
    "regex_features": []
  }
}